mypackage/__init__.py
mypackage/core.py
arya2513_passgen-0.1.0.dist-info/METADATA
arya2513_passgen-0.1.0.dist-info/WHEEL
arya2513_passgen-0.1.0.dist-info/RECORD
