Metadata-Version: 2.4
Name: arya2513-passgen
Version: 0.1.0
Summary: A simple random password generator.
Project-URL: Homepage, https://github.com/arya2513/Pypi-project
Project-URL: Issues, https://github.com/arya2513/Pypi-project/issues
Author: Your Name
License: MIT
Keywords: generator,password,security
Classifier: License :: OSI Approved :: MIT License
Classifier: Programming Language :: Python :: 3
Requires-Python: >=3.8
